Isconna/EdgeNodeCore.py
Isconna/EdgeOnlyCore.py
Isconna/__init__.py
Isconna-1.1.0.dist-info/LICENSE
Isconna-1.1.0.dist-info/METADATA
Isconna-1.1.0.dist-info/WHEEL
Isconna-1.1.0.dist-info/top_level.txt
Isconna-1.1.0.dist-info/RECORD
