Metadata-Version: 2.1
Name: Isconna
Version: 1.1.0
Summary: Python porting of the Isconna algorithm
Home-page: https://github.com/liurui39660/Isconna.Python
Author: Rui LIU
Author-email: xxliuruiabc@gmail.com
License: UNKNOWN
Platform: UNKNOWN
Classifier: Intended Audience :: Science/Research
Classifier: License :: OSI Approved :: Apache Software License
Classifier: Operating System :: OS Independent
Classifier: Programming Language :: Python :: 3
Requires-Python: >=3.6
License-File: LICENSE
Requires-Dist: numba
Requires-Dist: numpy
